README.rst
setup.py
rlj/__init__.py
rlj/config.py
rlj/constants.py
rlj/judge.py
rlj/language.py
rlj/languages.py
rlj/main.py
rlj/output.py
rlj.egg-info/PKG-INFO
rlj.egg-info/SOURCES.txt
rlj.egg-info/dependency_links.txt
rlj.egg-info/entry_points.txt
rlj.egg-info/requires.txt
rlj.egg-info/top_level.txt
tests/__init__.py
tests/tests.py