Metadata-Version: 1.1
Name: rlj
Version: 1.4.1
Summary: A Local Judge for OIers and ACMers by _rqy
Home-page: https://github.com/rqy1458814497/RLJ/
Author: _rqy
Author-email: 1458814497@qq.com
License: MIT Linsence
Platform: UNKNOWN
Classifier: Development Status :: 3 - Alpha
Classifier: Programming Language :: Python
Classifier: Programming Language :: Python :: 3
Classifier: Programming Language :: Python :: 3.1
Classifier: Programming Language :: Python :: 3.2
Classifier: Programming Language :: Python :: 3.3
Classifier: Programming Language :: Python :: 3.4
Classifier: Programming Language :: Python :: 3.5
Classifier: Programming Language :: Python :: 3.6
Classifier: Environment :: Console
Classifier: License :: OSI Approved :: MIT License
Classifier: Intended Audience :: Information Technology
